securag/__init__.py
securag/exceptions.py
securag/executor/__init__.py
securag/executor/executor.py
securag/modules/__init__.py
securag/modules/module_base.py
securag/modules/filtering/__init__.py
securag/modules/filtering/http_filter.py
securag/modules/filtering/input_filtering_base.py
securag/modules/filtering/keyword_filter.py
securag/modules/sanitizer/__init__.py
securag/modules/sanitizer/sanitizer_base.py
securag/pipe/__init__.py
securag/pipe/pipe_base.py
securag/pipe/process_pipe.py
securag/pipe/sequential_pipe.py
securag/pipe/thread_pipe.py
securag/pipe/thread_process_pipe.py
securag-0.0.1.dist-info/METADATA
securag-0.0.1.dist-info/WHEEL
securag-0.0.1.dist-info/top_level.txt
securag-0.0.1.dist-info/RECORD
