Metadata-Version: 2.4
Name: securag
Version: 0.0.1
Summary: SECURAG
Home-page: https://github.com/pavanreddyml/secuRAG
Author: Pavan Reddy
Author-email: preddy.osdev@gmail.com
License: MIT
Classifier: Programming Language :: Python :: 3
Classifier: License :: OSI Approved :: MIT License
Classifier: Operating System :: OS Independent
Requires-Python: >=3.11
Requires-Dist: ollama
Requires-Dist: requests
Requires-Dist: pydantic
Requires-Dist: python-dotenv
Requires-Dist: jmespath
Dynamic: author
Dynamic: author-email
Dynamic: classifier
Dynamic: description-content-type
Dynamic: home-page
Dynamic: license
Dynamic: requires-dist
Dynamic: requires-python
Dynamic: summary
